dict_from_dragonmapper/__init__.py
dict_from_dragonmapper/argparse_helper.py
dict_from_dragonmapper/cli.py
dict_from_dragonmapper/ipa2symb.py
dict_from_dragonmapper/ipa_symbols.py
dict_from_dragonmapper/main.py
dict_from_dragonmapper-0.0.2.dist-info/LICENSE
dict_from_dragonmapper-0.0.2.dist-info/METADATA
dict_from_dragonmapper-0.0.2.dist-info/WHEEL
dict_from_dragonmapper-0.0.2.dist-info/entry_points.txt
dict_from_dragonmapper-0.0.2.dist-info/top_level.txt
dict_from_dragonmapper-0.0.2.dist-info/RECORD
