Metadata-Version: 2.1
Name: dict-from-dragonmapper
Version: 0.0.2
Summary: Command-line interface (CLI) to create a pronunciation dictionary by looking up IPA transcriptions using dragonmapper including the possibility of ignoring punctuation and splitting words on hyphens before transcribing them.
Author: Stefan Taubert
Author-email: pypi@stefantaubert.com
Maintainer: Stefan Taubert
Maintainer-email: pypi@stefantaubert.com
License: MIT
Project-URL: Homepage, https://github.com/stefantaubert/dict-from-dragonmapper
Project-URL: Issues, https://github.com/stefantaubert/dict-from-dragonmapper/issues
Keywords: Pronunciation,Dictionary,Chinese,IPA,Language,Linguistics
Classifier: Development Status :: 2 - Pre-Alpha
Classifier: Operating System :: OS Independent
Classifier: Operating System :: MacOS
Classifier: Operating System :: POSIX
Classifier: Operating System :: POSIX :: BSD
Classifier: Operating System :: POSIX :: Linux
Classifier: Operating System :: Unix
Classifier: Operating System :: Microsoft :: Windows
Classifier: Programming Language :: Python
Classifier: Programming Language :: Python :: 3
Classifier: Programming Language :: Python :: 3.8
Classifier: Programming Language :: Python :: 3.9
Classifier: Programming Language :: Python :: 3.10
Classifier: License :: OSI Approved :: MIT License
Requires-Python: >=3.8
License-File: LICENSE
Requires-Dist: pronunciation-dictionary (>=0.0.4)
Requires-Dist: ordered-set (>=4.1.0)
Requires-Dist: word-to-pronunciation (>=0.0.1)
Requires-Dist: dragonmapper (<0.3,>=0.2.6)
Requires-Dist: tqdm
